latex_generator_for_tables_and_images/__init__.py
latex_generator_for_tables_and_images/generator.py
latex_generator_for_tables_and_images-0.0.2.dist-info/METADATA
latex_generator_for_tables_and_images-0.0.2.dist-info/WHEEL
latex_generator_for_tables_and_images-0.0.2.dist-info/top_level.txt
latex_generator_for_tables_and_images-0.0.2.dist-info/RECORD
