Metadata-Version: 2.1
Name: latex-generator-for-tables-and-images
Version: 0.0.2
Summary: A library to generate code for tables and images.
Home-page: https://example.com
Author: Artem
Author-email: Artems2311@mail.ru
License: UNKNOWN
Platform: UNKNOWN
Classifier: Programming Language :: Python :: 3.11
Classifier: License :: OSI Approved :: MIT License
Classifier: Operating System :: OS Independent
Requires-Python: >=3.6
Requires-Dist: requests>=2.25.1
